fhl_bible_api/__init__.py
fhl_bible_api/client.py
fhl_bible_api/constants.py
fhl_bible_api/exceptions.py
fhl_bible_api/models.py
fhl_bible_api/py.typed
fhl_bible_api-0.2.0.dist-info/METADATA
fhl_bible_api-0.2.0.dist-info/WHEEL
fhl_bible_api-0.2.0.dist-info/licenses/LICENSE
fhl_bible_api-0.2.0.dist-info/RECORD
