Metadata-Version: 2.4
Name: fhl-bible-api
Version: 0.2.0
Summary: A Python client for the Faith, Hope, Love (FHL) Bible API - 台灣信望愛聖經API的Python客戶端
Project-URL: Homepage, https://gitlab.com/cwchiu/fhl-bible-api-py
Project-URL: Documentation, https://gitlab.com/cwchiu/fhl-bible-api-py
Project-URL: Repository, https://gitlab.com/cwchiu/fhl-bible-api-py
Project-URL: Issues, https://gitlab.com/cwchiu/fhl-bible-api-py/-/issues
Author-email: arick <arick@gmail.com>
License: MIT
License-File: LICENSE
Keywords: api-client,bible,christianity,faith-hope-love,fhl
Classifier: Development Status :: 4 - Beta
Classifier: Intended Audience :: Developers
Classifier: Intended Audience :: Religion
Classifier: License :: OSI Approved :: MIT License
Classifier: Operating System :: OS Independent
Classifier: Programming Language :: Python :: 3
Classifier: Programming Language :: Python :: 3.12
Classifier: Programming Language :: Python :: 3.13
Classifier: Topic :: Religion
Classifier: Topic :: Software Development :: Libraries :: Python Modules
Classifier: Typing :: Typed
Requires-Python: >=3.12
Requires-Dist: httpx>=0.27.0
Provides-Extra: dev
Requires-Dist: mypy>=1.8.0; extra == 'dev'
Requires-Dist: ruff>=0.8.0; extra == 'dev'
Provides-Extra: test
Requires-Dist: pytest-asyncio>=0.23.0; extra == 'test'
Requires-Dist: pytest-cov>=4.1.0; extra == 'test'
Requires-Dist: pytest>=8.0.0; extra == 'test'
